ofxstatement_intesasp-0.3.0-py3.13-nspkg.pth
ofxstatement/plugins/intesaSP.py
ofxstatement_intesasp-0.3.0.dist-info/METADATA
ofxstatement_intesasp-0.3.0.dist-info/WHEEL
ofxstatement_intesasp-0.3.0.dist-info/entry_points.txt
ofxstatement_intesasp-0.3.0.dist-info/namespace_packages.txt
ofxstatement_intesasp-0.3.0.dist-info/top_level.txt
ofxstatement_intesasp-0.3.0.dist-info/zip-safe
ofxstatement_intesasp-0.3.0.dist-info/RECORD
