Metadata-Version: 2.2
Name: ofxstatement-intesasp
Version: 0.3.0
Summary: Plugin for ofxstatement that supports Intesa San paolo xlsx file
Home-page: https://github.com/Jacotsu/ofxstatement-intesasp
Author: Di Campli D. Raffaele Jr
Author-email: dcdrj.pub@gmail.com
License: GPLv3
Keywords: ofx,banking,statement
Classifier: Development Status :: 3 - Alpha
Classifier: Programming Language :: Python :: 3.6
Classifier: Natural Language :: English
Classifier: Topic :: Office/Business :: Financial :: Accounting
Classifier: Topic :: Utilities
Classifier: Environment :: Console
Classifier: Operating System :: OS Independent
Classifier: License :: OSI Approved :: GNU General Public License v3 (GPLv3)
Requires-Dist: ofxstatement
Requires-Dist: openpyxl
Requires-Dist: dataclasses
Dynamic: author
Dynamic: author-email
Dynamic: classifier
Dynamic: description
Dynamic: description-content-type
Dynamic: home-page
Dynamic: keywords
Dynamic: license
Dynamic: requires-dist
Dynamic: summary
